[
  {
    "table_pos": 64,
    "mode": "A",
    "start": 2333,
    "length": 3,
    "end": 2336,
    "text": "001"
  },
  {
    "table_pos": 80,
    "mode": "B-implicit",
    "start": 2336,
    "length": 10,
    "end": 2346,
    "text": "Konohamaru"
  },
  {
    "table_pos": 80,
    "mode": "B-explicit",
    "start": 2346,
    "length": 20,
    "end": 2366,
    "text": "Estava te esperando!"
  },
  {
    "table_pos": 96,
    "mode": "A",
    "start": 2366,
    "length": 0,
    "end": 2366,
    "text": ""
  },
  {
    "table_pos": 112,
    "mode": "A",
    "start": 2366,
    "length": 3,
    "end": 2369,
    "text": "002"
  },
  {
    "table_pos": 128,
    "mode": "B-implicit",
    "start": 2369,
    "length": 6,
    "end": 2375,
    "text": "Naruto"
  },
  {
    "table_pos": 128,
    "mode": "B-explicit",
    "start": 2375,
    "length": 72,
    "end": 2447,
    "text": "Está me desafiando de novo mesmo\nperdendo sempre? Você é\npersistente."
  },
  {
    "table_pos": 144,
    "mode": "A",
    "start": 2447,
    "length": 0,
    "end": 2447,
    "text": ""
  },
  {
    "table_pos": 160,
    "mode": "A",
    "start": 2447,
    "length": 3,
    "end": 2450,
    "text": "003"
  },
  {
    "table_pos": 176,
    "mode": "B-implicit",
    "start": 2450,
    "length": 10,
    "end": 2460,
    "text": "Konohamaru"
  },
  {
    "table_pos": 176,
    "mode": "B-explicit",
    "start": 2460,
    "length": 68,
    "end": 2528,
    "text": "Foi você quem disse que me daria\nrevanche a qualquer hora, lembra!?"
  },
  {
    "table_pos": 192,
    "mode": "A",
    "start": 2528,
    "length": 0,
    "end": 2528,
    "text": ""
  },
  {
    "table_pos": 208,
    "mode": "A",
    "start": 2528,
    "length": 3,
    "end": 2531,
    "text": "004"
  },
  {
    "table_pos": 224,
    "mode": "B-implicit",
    "start": 2531,
    "length": 6,
    "end": 2537,
    "text": "Naruto"
  },
  {
    "table_pos": 224,
    "mode": "B-explicit",
    "start": 2537,
    "length": 30,
    "end": 2567,
    "text": "Bem, é, eu disse isso, mas..."
  },
  {
    "table_pos": 240,
    "mode": "A",
    "start": 2567,
    "length": 0,
    "end": 2567,
    "text": ""
  },
  {
    "table_pos": 256,
    "mode": "A",
    "start": 2567,
    "length": 3,
    "end": 2570,
    "text": "005"
  },
  {
    "table_pos": 272,
    "mode": "B-implicit",
    "start": 2570,
    "length": 10,
    "end": 2580,
    "text": "Konohamaru"
  },
  {
    "table_pos": 272,
    "mode": "B-explicit",
    "start": 2580,
    "length": 28,
    "end": 2608,
    "text": "Sua palavra é sua garantia!"
  },
  {
    "table_pos": 288,
    "mode": "A",
    "start": 2608,
    "length": 0,
    "end": 2608,
    "text": ""
  },
  {
    "table_pos": 304,
    "mode": "A",
    "start": 2608,
    "length": 3,
    "end": 2611,
    "text": "006"
  },
  {
    "table_pos": 320,
    "mode": "B-implicit",
    "start": 2611,
    "length": 6,
    "end": 2617,
    "text": "Naruto"
  },
  {
    "table_pos": 320,
    "mode": "B-explicit",
    "start": 2617,
    "length": 17,
    "end": 2634,
    "text": "Hm... Isso mesmo!"
  },
  {
    "table_pos": 336,
    "mode": "A",
    "start": 2634,
    "length": 0,
    "end": 2634,
    "text": ""
  },
  {
    "table_pos": 352,
    "mode": "A",
    "start": 2634,
    "length": 3,
    "end": 2637,
    "text": "007"
  },
  {
    "table_pos": 368,
    "mode": "B-implicit",
    "start": 2637,
    "length": 10,
    "end": 2647,
    "text": "Konohamaru"
  },
  {
    "table_pos": 368,
    "mode": "B-explicit",
    "start": 2647,
    "length": 68,
    "end": 2715,
    "text": "Finalmente terei minha revanche!!\nAliás, a Moegi está no meu time!"
  },
  {
    "table_pos": 384,
    "mode": "A",
    "start": 2715,
    "length": 0,
    "end": 2715,
    "text": ""
  },
  {
    "table_pos": 400,
    "mode": "A",
    "start": 2715,
    "length": 3,
    "end": 2718,
    "text": "008"
  },
  {
    "table_pos": 416,
    "mode": "B-implicit",
    "start": 2718,
    "length": 5,
    "end": 2723,
    "text": "Moegi"
  },
  {
    "table_pos": 416,
    "mode": "B-explicit",
    "start": 2723,
    "length": 27,
    "end": 2750,
    "text": "Eu não vou perder, Naruto!"
  },
  {
    "table_pos": 432,
    "mode": "A",
    "start": 2750,
    "length": 0,
    "end": 2750,
    "text": ""
  },
  {
    "table_pos": 448,
    "mode": "A",
    "start": 2750,
    "length": 3,
    "end": 2753,
    "text": "009"
  },
  {
    "table_pos": 464,
    "mode": "B-implicit",
    "start": 2753,
    "length": 6,
    "end": 2759,
    "text": "Naruto"
  },
  {
    "table_pos": 464,
    "mode": "B-explicit",
    "start": 2759,
    "length": 26,
    "end": 2785,
    "text": "Tá, aceito o seu desafio!"
  },
  {
    "table_pos": 480,
    "mode": "A",
    "start": 2785,
    "length": 0,
    "end": 2785,
    "text": ""
  },
  {
    "table_pos": 496,
    "mode": "A",
    "start": 2785,
    "length": 3,
    "end": 2788,
    "text": "010"
  },
  {
    "table_pos": 512,
    "mode": "B-implicit",
    "start": 2788,
    "length": 10,
    "end": 2798,
    "text": "Konohamaru"
  },
  {
    "table_pos": 512,
    "mode": "B-explicit",
    "start": 2798,
    "length": 73,
    "end": 2871,
    "text": "Então não há mais nada a dizer...\nExceto que dessa vez, eu vou vencer!"
  },
  {
    "table_pos": 528,
    "mode": "A",
    "start": 2871,
    "length": 0,
    "end": 2871,
    "text": ""
  },
  {
    "table_pos": 544,
    "mode": "A",
    "start": 2871,
    "length": 3,
    "end": 2874,
    "text": "011"
  },
  {
    "table_pos": 560,
    "mode": "B-implicit",
    "start": 2874,
    "length": 6,
    "end": 2880,
    "text": "Naruto"
  },
  {
    "table_pos": 560,
    "mode": "B-explicit",
    "start": 2880,
    "length": 30,
    "end": 2910,
    "text": "Pode ir, vou te achar de novo."
  },
  {
    "table_pos": 576,
    "mode": "A",
    "start": 2910,
    "length": 0,
    "end": 2910,
    "text": ""
  },
  {
    "table_pos": 592,
    "mode": "A",
    "start": 2910,
    "length": 3,
    "end": 2913,
    "text": "012"
  },
  {
    "table_pos": 608,
    "mode": "B-implicit",
    "start": 2913,
    "length": 10,
    "end": 2923,
    "text": "Konohamaru"
  },
  {
    "table_pos": 608,
    "mode": "B-explicit",
    "start": 2923,
    "length": 22,
    "end": 2945,
    "text": "Certo. Vamos começar!"
  },
  {
    "table_pos": 624,
    "mode": "A",
    "start": 2945,
    "length": 0,
    "end": 2945,
    "text": ""
  },
  {
    "table_pos": 640,
    "mode": "A",
    "start": 2945,
    "length": 3,
    "end": 2948,
    "text": "013"
  },
  {
    "table_pos": 656,
    "mode": "B-implicit",
    "start": 2948,
    "length": 6,
    "end": 2954,
    "text": "Naruto"
  },
  {
    "table_pos": 656,
    "mode": "B-explicit",
    "start": 2954,
    "length": 3,
    "end": 2957,
    "text": "..."
  },
  {
    "table_pos": 672,
    "mode": "A",
    "start": 2957,
    "length": 0,
    "end": 2957,
    "text": ""
  },
  {
    "table_pos": 688,
    "mode": "A",
    "start": 2957,
    "length": 3,
    "end": 2960,
    "text": "014"
  },
  {
    "table_pos": 704,
    "mode": "B-implicit",
    "start": 2960,
    "length": 6,
    "end": 2966,
    "text": "Naruto"
  },
  {
    "table_pos": 704,
    "mode": "B-explicit",
    "start": 2966,
    "length": 53,
    "end": 3019,
    "text": "Tempo esgotado! Lá vou eu,\nKonohamaru, Udon e Moegi!"
  },
  {
    "table_pos": 720,
    "mode": "A",
    "start": 3019,
    "length": 0,
    "end": 3019,
    "text": ""
  },
  {
    "table_pos": 736,
    "mode": "A",
    "start": 3019,
    "length": 3,
    "end": 3022,
    "text": "015"
  },
  {
    "table_pos": 752,
    "mode": "B-implicit",
    "start": 3022,
    "length": 6,
    "end": 3028,
    "text": "Naruto"
  },
  {
    "table_pos": 752,
    "mode": "B-explicit",
    "start": 3028,
    "length": 21,
    "end": 3049,
    "text": "Já acabou meu tempo?"
  },
  {
    "table_pos": 768,
    "mode": "A",
    "start": 3049,
    "length": 0,
    "end": 3049,
    "text": ""
  },
  {
    "table_pos": 784,
    "mode": "A",
    "start": 3049,
    "length": 3,
    "end": 3052,
    "text": "016"
  },
  {
    "table_pos": 800,
    "mode": "B-implicit",
    "start": 3052,
    "length": 6,
    "end": 3058,
    "text": "Naruto"
  },
  {
    "table_pos": 800,
    "mode": "B-explicit",
    "start": 3058,
    "length": 54,
    "end": 3112,
    "text": "Poxa... Achei que conseguiria\nfazer melhor que isso..."
  },
  {
    "table_pos": 816,
    "mode": "A",
    "start": 3112,
    "length": 0,
    "end": 3112,
    "text": ""
  },
  {
    "table_pos": 832,
    "mode": "A",
    "start": 3112,
    "length": 3,
    "end": 3115,
    "text": "017"
  },
  {
    "table_pos": 848,
    "mode": "B-implicit",
    "start": 3115,
    "length": 10,
    "end": 3125,
    "text": "Konohamaru"
  },
  {
    "table_pos": 848,
    "mode": "B-explicit",
    "start": 3125,
    "length": 37,
    "end": 3162,
    "text": "Sim! Consegui! Vitória! Vitória!!!!"
  },
  {
    "table_pos": 864,
    "mode": "A",
    "start": 3162,
    "length": 0,
    "end": 3162,
    "text": ""
  },
  {
    "table_pos": 880,
    "mode": "A",
    "start": 3162,
    "length": 3,
    "end": 3165,
    "text": "018"
  },
  {
    "table_pos": 896,
    "mode": "B-implicit",
    "start": 3165,
    "length": 6,
    "end": 3171,
    "text": "Naruto"
  },
  {
    "table_pos": 896,
    "mode": "B-explicit",
    "start": 3171,
    "length": 30,
    "end": 3201,
    "text": "Não precisa dizer duas vezes."
  },
  {
    "table_pos": 912,
    "mode": "A",
    "start": 3201,
    "length": 0,
    "end": 3201,
    "text": ""
  },
  {
    "table_pos": 928,
    "mode": "A",
    "start": 3201,
    "length": 3,
    "end": 3204,
    "text": "019"
  },
  {
    "table_pos": 944,
    "mode": "B-implicit",
    "start": 3204,
    "length": 4,
    "end": 3208,
    "text": "Udon"
  },
  {
    "table_pos": 944,
    "mode": "B-explicit",
    "start": 3208,
    "length": 23,
    "end": 3231,
    "text": "Mandou bem, Konohamaru!"
  },
  {
    "table_pos": 960,
    "mode": "A",
    "start": 3231,
    "length": 0,
    "end": 3231,
    "text": ""
  },
  {
    "table_pos": 976,
    "mode": "A",
    "start": 3231,
    "length": 3,
    "end": 3234,
    "text": "020"
  },
  {
    "table_pos": 992,
    "mode": "B-implicit",
    "start": 3234,
    "length": 5,
    "end": 3239,
    "text": "Moegi"
  },
  {
    "table_pos": 992,
    "mode": "B-explicit",
    "start": 3239,
    "length": 16,
    "end": 3255,
    "text": "Boa, Konohamaru!"
  },
  {
    "table_pos": 1008,
    "mode": "A",
    "start": 3255,
    "length": 0,
    "end": 3255,
    "text": ""
  },
  {
    "table_pos": 1024,
    "mode": "A",
    "start": 3255,
    "length": 3,
    "end": 3258,
    "text": "021"
  },
  {
    "table_pos": 1040,
    "mode": "B-implicit",
    "start": 3258,
    "length": 10,
    "end": 3268,
    "text": "Konohamaru"
  },
  {
    "table_pos": 1040,
    "mode": "B-explicit",
    "start": 3268,
    "length": 47,
    "end": 3315,
    "text": "Que sensação boa! Não acredito\nque vencemos!"
  },
  {
    "table_pos": 1056,
    "mode": "A",
    "start": 3315,
    "length": 0,
    "end": 3315,
    "text": ""
  },
  {
    "table_pos": 1072,
    "mode": "A",
    "start": 3315,
    "length": 3,
    "end": 3318,
    "text": "022"
  },
  {
    "table_pos": 1088,
    "mode": "B-implicit",
    "start": 3318,
    "length": 6,
    "end": 3324,
    "text": "Naruto"
  },
  {
    "table_pos": 1088,
    "mode": "B-explicit",
    "start": 3324,
    "length": 58,
    "end": 3382,
    "text": "Tá bom... Acho que preciso admitir\na derrota dessa vez..."
  },
  {
    "table_pos": 1104,
    "mode": "A",
    "start": 3382,
    "length": 0,
    "end": 3382,
    "text": ""
  },
  {
    "table_pos": 1120,
    "mode": "A",
    "start": 3382,
    "length": 3,
    "end": 3385,
    "text": "023"
  },
  {
    "table_pos": 1136,
    "mode": "B-implicit",
    "start": 3385,
    "length": 10,
    "end": 3395,
    "text": "Konohamaru"
  },
  {
    "table_pos": 1136,
    "mode": "B-explicit",
    "start": 3395,
    "length": 50,
    "end": 3445,
    "text": "Quer que eu pegue mais leve da\npróxima vez? Hihi!"
  },
  {
    "table_pos": 1152,
    "mode": "A",
    "start": 3445,
    "length": 0,
    "end": 3445,
    "text": ""
  },
  {
    "table_pos": 1168,
    "mode": "A",
    "start": 3445,
    "length": 3,
    "end": 3448,
    "text": "024"
  },
  {
    "table_pos": 1184,
    "mode": "B-implicit",
    "start": 3448,
    "length": 4,
    "end": 3452,
    "text": "Udon"
  },
  {
    "table_pos": 1184,
    "mode": "B-explicit",
    "start": 3452,
    "length": 55,
    "end": 3507,
    "text": "Excelente. Mal posso esperar\npra contar pra todo mundo."
  },
  {
    "table_pos": 1200,
    "mode": "A",
    "start": 3507,
    "length": 0,
    "end": 3507,
    "text": ""
  },
  {
    "table_pos": 1216,
    "mode": "A",
    "start": 3507,
    "length": 3,
    "end": 3510,
    "text": "025"
  },
  {
    "table_pos": 1232,
    "mode": "B-implicit",
    "start": 3510,
    "length": 5,
    "end": 3515,
    "text": "Moegi"
  },
  {
    "table_pos": 1232,
    "mode": "B-explicit",
    "start": 3515,
    "length": 39,
    "end": 3554,
    "text": "Fico feliz se o Konohamaru\nestá feliz!"
  },
  {
    "table_pos": 1248,
    "mode": "A",
    "start": 3554,
    "length": 0,
    "end": 3554,
    "text": ""
  },
  {
    "table_pos": 1264,
    "mode": "A",
    "start": 3554,
    "length": 3,
    "end": 3557,
    "text": "026"
  },
  {
    "table_pos": 1280,
    "mode": "B-implicit",
    "start": 3557,
    "length": 6,
    "end": 3563,
    "text": "Naruto"
  },
  {
    "table_pos": 1280,
    "mode": "B-explicit",
    "start": 3563,
    "length": 23,
    "end": 3586,
    "text": "Eu te vejo, Konohamaru!"
  },
  {
    "table_pos": 1296,
    "mode": "A",
    "start": 3586,
    "length": 0,
    "end": 3586,
    "text": ""
  },
  {
    "table_pos": 1312,
    "mode": "A",
    "start": 3586,
    "length": 3,
    "end": 3589,
    "text": "027"
  },
  {
    "table_pos": 1328,
    "mode": "B-implicit",
    "start": 3589,
    "length": 10,
    "end": 3599,
    "text": "Konohamaru"
  },
  {
    "table_pos": 1328,
    "mode": "B-explicit",
    "start": 3599,
    "length": 22,
    "end": 3621,
    "text": "Não... não pode ser!"
  },
  {
    "table_pos": 1344,
    "mode": "A",
    "start": 3621,
    "length": 0,
    "end": 3621,
    "text": ""
  },
  {
    "table_pos": 1360,
    "mode": "A",
    "start": 3621,
    "length": 3,
    "end": 3624,
    "text": "028"
  },
  {
    "table_pos": 1376,
    "mode": "B-implicit",
    "start": 3624,
    "length": 6,
    "end": 3630,
    "text": "Naruto"
  },
  {
    "table_pos": 1376,
    "mode": "B-explicit",
    "start": 3630,
    "length": 18,
    "end": 3648,
    "text": "Achei você, Udon!"
  },
  {
    "table_pos": 1392,
    "mode": "A",
    "start": 3648,
    "length": 0,
    "end": 3648,
    "text": ""
  },
  {
    "table_pos": 1408,
    "mode": "A",
    "start": 3648,
    "length": 3,
    "end": 3651,
    "text": "029"
  },
  {
    "table_pos": 1424,
    "mode": "B-implicit",
    "start": 3651,
    "length": 4,
    "end": 3655,
    "text": "Udon"
  },
  {
    "table_pos": 1424,
    "mode": "B-explicit",
    "start": 3655,
    "length": 42,
    "end": 3697,
    "text": "Aw... Achei que tinha te pego\ndessa vez..."
  },
  {
    "table_pos": 1440,
    "mode": "A",
    "start": 3697,
    "length": 0,
    "end": 3697,
    "text": ""
  },
  {
    "table_pos": 1456,
    "mode": "A",
    "start": 3697,
    "length": 3,
    "end": 3700,
    "text": "030"
  },
  {
    "table_pos": 1472,
    "mode": "B-implicit",
    "start": 3700,
    "length": 6,
    "end": 3706,
    "text": "Naruto"
  },
  {
    "table_pos": 1472,
    "mode": "B-explicit",
    "start": 3706,
    "length": 25,
    "end": 3731,
    "text": "Hihi! Achei você, Moegi!"
  },
  {
    "table_pos": 1488,
    "mode": "A",
    "start": 3731,
    "length": 0,
    "end": 3731,
    "text": ""
  },
  {
    "table_pos": 1504,
    "mode": "A",
    "start": 3731,
    "length": 3,
    "end": 3734,
    "text": "031"
  },
  {
    "table_pos": 1520,
    "mode": "B-implicit",
    "start": 3734,
    "length": 5,
    "end": 3739,
    "text": "Moegi"
  },
  {
    "table_pos": 1520,
    "mode": "B-explicit",
    "start": 3739,
    "length": 41,
    "end": 3780,
    "text": "Não pode ser! Achei que estava\nperfeita!"
  },
  {
    "table_pos": 1536,
    "mode": "A",
    "start": 3780,
    "length": 0,
    "end": 3780,
    "text": ""
  },
  {
    "table_pos": 1552,
    "mode": "A",
    "start": 3780,
    "length": 3,
    "end": 3783,
    "text": "032"
  },
  {
    "table_pos": 1568,
    "mode": "B-implicit",
    "start": 3783,
    "length": 6,
    "end": 3789,
    "text": "Naruto"
  },
  {
    "table_pos": 1568,
    "mode": "B-explicit",
    "start": 3789,
    "length": 28,
    "end": 3817,
    "text": "Tá bom... agora o próximo!"
  },
  {
    "table_pos": 1584,
    "mode": "A",
    "start": 3817,
    "length": 0,
    "end": 3817,
    "text": ""
  },
  {
    "table_pos": 1600,
    "mode": "A",
    "start": 3817,
    "length": 3,
    "end": 3820,
    "text": "033"
  },
  {
    "table_pos": 1616,
    "mode": "B-implicit",
    "start": 3820,
    "length": 6,
    "end": 3826,
    "text": "Naruto"
  },
  {
    "table_pos": 1616,
    "mode": "B-explicit",
    "start": 3826,
    "length": 44,
    "end": 3870,
    "text": "Naruto Olho-de-Águia Uzumaki\nvence de novo!"
  },
  {
    "table_pos": 1632,
    "mode": "A",
    "start": 3870,
    "length": 0,
    "end": 3870,
    "text": ""
  },
  {
    "table_pos": 1648,
    "mode": "A",
    "start": 3870,
    "length": 3,
    "end": 3873,
    "text": "034"
  },
  {
    "table_pos": 1664,
    "mode": "B-implicit",
    "start": 3873,
    "length": 10,
    "end": 3883,
    "text": "Konohamaru"
  },
  {
    "table_pos": 1664,
    "mode": "B-explicit",
    "start": 3883,
    "length": 30,
    "end": 3913,
    "text": "Nossa, Naruto... Você é bom!"
  },
  {
    "table_pos": 1680,
    "mode": "A",
    "start": 3913,
    "length": 0,
    "end": 3913,
    "text": ""
  },
  {
    "table_pos": 1696,
    "mode": "A",
    "start": 3913,
    "length": 3,
    "end": 3916,
    "text": "035"
  },
  {
    "table_pos": 1712,
    "mode": "B-implicit",
    "start": 3916,
    "length": 4,
    "end": 3920,
    "text": "Udon"
  },
  {
    "table_pos": 1712,
    "mode": "B-explicit",
    "start": 3920,
    "length": 46,
    "end": 3966,
    "text": "Hmm... Achei mesmo que tínhamos\nconseguido..."
  },
  {
    "table_pos": 1728,
    "mode": "A",
    "start": 3966,
    "length": 0,
    "end": 3966,
    "text": ""
  },
  {
    "table_pos": 1744,
    "mode": "A",
    "start": 3966,
    "length": 3,
    "end": 3969,
    "text": "036"
  },
  {
    "table_pos": 1760,
    "mode": "B-implicit",
    "start": 3969,
    "length": 5,
    "end": 3974,
    "text": "Moegi"
  },
  {
    "table_pos": 1760,
    "mode": "B-explicit",
    "start": 3974,
    "length": 21,
    "end": 3995,
    "text": "Você é bom, Naruto!"
  },
  {
    "table_pos": 1776,
    "mode": "A",
    "start": 3995,
    "length": 0,
    "end": 3995,
    "text": ""
  },
  {
    "table_pos": 1792,
    "mode": "A",
    "start": 3995,
    "length": 3,
    "end": 3998,
    "text": "037"
  },
  {
    "table_pos": 1808,
    "mode": "B-implicit",
    "start": 3998,
    "length": 6,
    "end": 4004,
    "text": "Naruto"
  },
  {
    "table_pos": 1808,
    "mode": "B-explicit",
    "start": 4004,
    "length": 52,
    "end": 4056,
    "text": "Mas vocês estão ficando muito bons\nem se esconder!"
  },
  {
    "table_pos": 1824,
    "mode": "A",
    "start": 4056,
    "length": 0,
    "end": 4056,
    "text": ""
  },
  {
    "table_pos": 1840,
    "mode": "A",
    "start": 4056,
    "length": 3,
    "end": 4059,
    "text": "038"
  },
  {
    "table_pos": 1856,
    "mode": "B-implicit",
    "start": 4059,
    "length": 6,
    "end": 4065,
    "text": "Naruto"
  },
  {
    "table_pos": 1856,
    "mode": "B-explicit",
    "start": 4065,
    "length": 20,
    "end": 4085,
    "text": "Estou impressionado."
  },
  {
    "table_pos": 1872,
    "mode": "A",
    "start": 4085,
    "length": 0,
    "end": 4085,
    "text": ""
  },
  {
    "table_pos": 1888,
    "mode": "A",
    "start": 4085,
    "length": 3,
    "end": 4088,
    "text": "039"
  },
  {
    "table_pos": 1904,
    "mode": "B-implicit",
    "start": 4088,
    "length": 10,
    "end": 4098,
    "text": "Konohamaru"
  },
  {
    "table_pos": 1904,
    "mode": "B-explicit",
    "start": 4098,
    "length": 42,
    "end": 4140,
    "text": "Vindo de você, isso é um elogio\ne tanto!"
  },
  {
    "table_pos": 1920,
    "mode": "A",
    "start": 4140,
    "length": 0,
    "end": 4140,
    "text": ""
  },
  {
    "table_pos": 1936,
    "mode": "A",
    "start": 4140,
    "length": 3,
    "end": 4143,
    "text": "040"
  },
  {
    "table_pos": 1952,
    "mode": "B-implicit",
    "start": 4143,
    "length": 5,
    "end": 4148,
    "text": "Moegi"
  },
  {
    "table_pos": 1952,
    "mode": "B-explicit",
    "start": 4148,
    "length": 4,
    "end": 4152,
    "text": "Sim!"
  },
  {
    "table_pos": 1968,
    "mode": "A",
    "start": 4152,
    "length": 0,
    "end": 4152,
    "text": ""
  },
  {
    "table_pos": 1984,
    "mode": "A",
    "start": 4152,
    "length": 3,
    "end": 4155,
    "text": "041"
  },
  {
    "table_pos": 2000,
    "mode": "B-implicit",
    "start": 4155,
    "length": 6,
    "end": 4161,
    "text": "Naruto"
  },
  {
    "table_pos": 2000,
    "mode": "B-explicit",
    "start": 4161,
    "length": 60,
    "end": 4221,
    "text": "Konohamaru, Udon, Moegi! Vamos\nfazer isso de novo algum dia!"
  },
  {
    "table_pos": 2016,
    "mode": "A",
    "start": 4221,
    "length": 0,
    "end": 4221,
    "text": ""
  },
  {
    "table_pos": 2032,
    "mode": "A",
    "start": 4221,
    "length": 3,
    "end": 4224,
    "text": "042"
  },
  {
    "table_pos": 2048,
    "mode": "B-implicit",
    "start": 4224,
    "length": 10,
    "end": 4234,
    "text": "Konohamaru"
  },
  {
    "table_pos": 2048,
    "mode": "B-explicit",
    "start": 4234,
    "length": 21,
    "end": 4255,
    "text": "Hahaha... Combinado!!"
  },
  {
    "table_pos": 2064,
    "mode": "A",
    "start": 4255,
    "length": 0,
    "end": 4255,
    "text": ""
  },
  {
    "table_pos": 2080,
    "mode": "A",
    "start": 4255,
    "length": 3,
    "end": 4258,
    "text": "043"
  },
  {
    "table_pos": 2096,
    "mode": "B-implicit",
    "start": 4258,
    "length": 10,
    "end": 4268,
    "text": "Konohamaru"
  },
  {
    "table_pos": 2096,
    "mode": "B-explicit",
    "start": 4268,
    "length": 50,
    "end": 4318,
    "text": "Afinal, eu realmente gosto de\ncurtir com o Naruto!"
  },
  {
    "table_pos": 2112,
    "mode": "A",
    "start": 4318,
    "length": 0,
    "end": 4318,
    "text": ""
  },
  {
    "table_pos": 2128,
    "mode": "A",
    "start": 4318,
    "length": 3,
    "end": 4321,
    "text": "044"
  },
  {
    "table_pos": 2144,
    "mode": "B-implicit",
    "start": 4321,
    "length": 4,
    "end": 4325,
    "text": "Udon"
  },
  {
    "table_pos": 2144,
    "mode": "B-explicit",
    "start": 4325,
    "length": 25,
    "end": 4350,
    "text": "O Naruto é tão legal..."
  },
  {
    "table_pos": 2160,
    "mode": "A",
    "start": 4350,
    "length": 0,
    "end": 4350,
    "text": ""
  },
  {
    "table_pos": 2176,
    "mode": "A",
    "start": 4350,
    "length": 3,
    "end": 4353,
    "text": "045"
  },
  {
    "table_pos": 2192,
    "mode": "B-implicit",
    "start": 4353,
    "length": 5,
    "end": 4358,
    "text": "Moegi"
  },
  {
    "table_pos": 2192,
    "mode": "B-explicit",
    "start": 4358,
    "length": 50,
    "end": 4408,
    "text": "Não é à toa que o Konohamaru quer\nser como ele!"
  },
  {
    "table_pos": 2208,
    "mode": "A",
    "start": 4408,
    "length": 0,
    "end": 4408,
    "text": ""
  }
]